{
  "updatedAt": "2026-03-16T14:00:25.756Z",
  "categories": [
    {
      "name": "AI Semiconductors",
      "id": "semiconductor",
      "stocks": [
        {
          "symbol": "NVDA",
          "name": "NVIDIA",
          "price": 184.31,
          "change": 4.060000000000002,
          "changePercent": 2.2524271844660206
        },
        {
          "symbol": "AMD",
          "name": "AMD",
          "price": 196.73,
          "change": 3.3400000000000034,
          "changePercent": 1.727079993794924
        },
        {
          "symbol": "INTC",
          "name": "Intel",
          "price": 47.89,
          "change": 2.1199999999999974,
          "changePercent": 4.6318549268079465
        },
        {
          "symbol": "QCOM",
          "name": "Qualcomm",
          "price": 129.52,
          "change": -0.29999999999998295,
          "changePercent": -0.23108920043135336
        },
        {
          "symbol": "AVGO",
          "name": "Broadcom",
          "price": 323.45,
          "change": 1.2899999999999636,
          "changePercent": 0.40042215048422014
        },
        {
          "symbol": "TSM",
          "name": "TSMC",
          "price": 342.095,
          "change": 3.785000000000025,
          "changePercent": 1.1187963701930255
        },
        {
          "symbol": "ARM",
          "name": "Arm Holdings",
          "price": 119.121,
          "change": 3.370999999999995,
          "changePercent": 2.912311015118786
        }
      ]
    },
    {
      "name": "Big Tech",
      "id": "bigtech",
      "stocks": [
        {
          "symbol": "MSFT",
          "name": "Microsoft",
          "price": 395.24,
          "change": -0.3100000000000023,
          "changePercent": -0.07837188724560795
        },
        {
          "symbol": "GOOGL",
          "name": "Alphabet",
          "price": 305.089,
          "change": 2.809000000000026,
          "changePercent": 0.9292708746857306
        },
        {
          "symbol": "META",
          "name": "Meta",
          "price": 629.84,
          "change": 16.655000000000086,
          "changePercent": 2.716146024446144
        },
        {
          "symbol": "AMZN",
          "name": "Amazon",
          "price": 208.68,
          "change": 1.0100000000000193,
          "changePercent": 0.48634853373141007
        },
        {
          "symbol": "AAPL",
          "name": "Apple",
          "price": 252.79,
          "change": 2.6699999999999875,
          "changePercent": 1.0674876059491394
        }
      ]
    },
    {
      "name": "AI Pure-Play",
      "id": "ai-pure",
      "stocks": [
        {
          "symbol": "PLTR",
          "name": "Palantir",
          "price": 151.93,
          "change": 0.9800000000000182,
          "changePercent": 0.6492215965551629
        },
        {
          "symbol": "AI",
          "name": "C3.ai",
          "price": 8.885,
          "change": -0.025000000000000355,
          "changePercent": -0.28058361391695125
        },
        {
          "symbol": "SNOW",
          "name": "Snowflake",
          "price": 176.617,
          "change": -2.0430000000000064,
          "changePercent": -1.143512817642453
        },
        {
          "symbol": "PATH",
          "name": "UiPath",
          "price": 11.565,
          "change": -0.015000000000000568,
          "changePercent": -0.12953367875648159
        },
        {
          "symbol": "DDOG",
          "name": "Datadog",
          "price": 127.93,
          "change": 3.410000000000011,
          "changePercent": 2.7385159010600795
        }
      ]
    }
  ]
}