{
  "updatedAt": "2026-03-19T17:00:23.049Z",
  "categories": [
    {
      "name": "AI Semiconductors",
      "id": "semiconductor",
      "stocks": [
        {
          "symbol": "NVDA",
          "name": "NVIDIA",
          "price": 178.125,
          "change": -2.2750000000000057,
          "changePercent": -1.2610864745011119
        },
        {
          "symbol": "AMD",
          "name": "AMD",
          "price": 200.54,
          "change": 1.079999999999984,
          "changePercent": 0.5414619472575875
        },
        {
          "symbol": "INTC",
          "name": "Intel",
          "price": 45.58,
          "change": 0.5499999999999972,
          "changePercent": 1.221407950255379
        },
        {
          "symbol": "QCOM",
          "name": "Qualcomm",
          "price": 131.15,
          "change": 0.6800000000000068,
          "changePercent": 0.52119261132828
        },
        {
          "symbol": "AVGO",
          "name": "Broadcom",
          "price": 319.135,
          "change": 3.204999999999984,
          "changePercent": 1.014465229639472
        },
        {
          "symbol": "TSM",
          "name": "TSMC",
          "price": 333.84,
          "change": -5.730000000000018,
          "changePercent": -1.687428218040468
        },
        {
          "symbol": "ARM",
          "name": "Arm Holdings",
          "price": 128,
          "change": -0.36000000000001364,
          "changePercent": -0.2804612028669473
        }
      ]
    },
    {
      "name": "Big Tech",
      "id": "bigtech",
      "stocks": [
        {
          "symbol": "MSFT",
          "name": "Microsoft",
          "price": 388.55,
          "change": -3.240000000000009,
          "changePercent": -0.8269736338344544
        },
        {
          "symbol": "GOOGL",
          "name": "Alphabet",
          "price": 306.2,
          "change": -1.490000000000009,
          "changePercent": -0.4842536319022422
        },
        {
          "symbol": "META",
          "name": "Meta",
          "price": 606.56,
          "change": -9.120000000000005,
          "changePercent": -1.481288981288982
        },
        {
          "symbol": "AMZN",
          "name": "Amazon",
          "price": 207.3,
          "change": -2.569999999999993,
          "changePercent": -1.2245675894601387
        },
        {
          "symbol": "AAPL",
          "name": "Apple",
          "price": 248.11,
          "change": -1.829999999999984,
          "changePercent": -0.7321757221733153
        }
      ]
    },
    {
      "name": "AI Pure-Play",
      "id": "ai-pure",
      "stocks": [
        {
          "symbol": "PLTR",
          "name": "Palantir",
          "price": 153.825,
          "change": 1.0549999999999784,
          "changePercent": 0.690580611376565
        },
        {
          "symbol": "AI",
          "name": "C3.ai",
          "price": 8.535,
          "change": -0.07499999999999929,
          "changePercent": -0.8710801393728141
        },
        {
          "symbol": "SNOW",
          "name": "Snowflake",
          "price": 173.16,
          "change": -0.09000000000000341,
          "changePercent": -0.05194805194805392
        },
        {
          "symbol": "PATH",
          "name": "UiPath",
          "price": 12.145,
          "change": -0.3049999999999997,
          "changePercent": -2.449799196787146
        },
        {
          "symbol": "DDOG",
          "name": "Datadog",
          "price": 127.37,
          "change": -3.8899999999999864,
          "changePercent": -2.9635837269541265
        }
      ]
    }
  ]
}