{
  "updatedAt": "2026-02-24T17:00:21.010Z",
  "categories": [
    {
      "name": "AI Semiconductors",
      "id": "semiconductor",
      "stocks": [
        {
          "symbol": "NVDA",
          "name": "NVIDIA",
          "price": 192.975,
          "change": 1.424999999999983,
          "changePercent": 0.7439310884886363
        },
        {
          "symbol": "AMD",
          "name": "AMD",
          "price": 212.77,
          "change": 16.170000000000016,
          "changePercent": 8.224821973550364
        },
        {
          "symbol": "INTC",
          "name": "Intel",
          "price": 45.679,
          "change": 2.0489999999999995,
          "changePercent": 4.69630987852395
        },
        {
          "symbol": "QCOM",
          "name": "Qualcomm",
          "price": 144.44,
          "change": 4.030000000000001,
          "changePercent": 2.870165942596682
        },
        {
          "symbol": "AVGO",
          "name": "Broadcom",
          "price": 326.875,
          "change": -3.464999999999975,
          "changePercent": -1.048919295271531
        },
        {
          "symbol": "TSM",
          "name": "TSMC",
          "price": 386.88,
          "change": 16.839999999999975,
          "changePercent": 4.55085936655496
        },
        {
          "symbol": "ARM",
          "name": "Arm Holdings",
          "price": 128.68,
          "change": 4.900000000000006,
          "changePercent": 3.9586362901922816
        }
      ]
    },
    {
      "name": "Big Tech",
      "id": "bigtech",
      "stocks": [
        {
          "symbol": "MSFT",
          "name": "Microsoft",
          "price": 386.11,
          "change": 1.6399999999999864,
          "changePercent": 0.4265612401487727
        },
        {
          "symbol": "GOOGL",
          "name": "Alphabet",
          "price": 311,
          "change": -0.4900000000000091,
          "changePercent": -0.15730842081608049
        },
        {
          "symbol": "META",
          "name": "Meta",
          "price": 638.98,
          "change": 1.7300000000000182,
          "changePercent": 0.2714790113770134
        },
        {
          "symbol": "AMZN",
          "name": "Amazon",
          "price": 209.187,
          "change": 3.9170000000000016,
          "changePercent": 1.9082184440005854
        },
        {
          "symbol": "AAPL",
          "name": "Apple",
          "price": 272.335,
          "change": 6.154999999999973,
          "changePercent": 2.3123450296791543
        }
      ]
    },
    {
      "name": "AI Pure-Play",
      "id": "ai-pure",
      "stocks": [
        {
          "symbol": "PLTR",
          "name": "Palantir",
          "price": 129.235,
          "change": -1.3649999999999807,
          "changePercent": -1.045176110260322
        },
        {
          "symbol": "AI",
          "name": "C3.ai",
          "price": 9.855,
          "change": 0.06500000000000128,
          "changePercent": 0.6639427987742726
        },
        {
          "symbol": "SNOW",
          "name": "Snowflake",
          "price": 162.785,
          "change": 5.185000000000002,
          "changePercent": 3.2899746192893415
        },
        {
          "symbol": "PATH",
          "name": "UiPath",
          "price": 10.186,
          "change": 0.016000000000000014,
          "changePercent": 0.15732546705998046
        },
        {
          "symbol": "DDOG",
          "name": "Datadog",
          "price": 104.37,
          "change": 1.7550000000000097,
          "changePercent": 1.7102762753983431
        }
      ]
    }
  ]
}