{
  "updatedAt": "2026-04-01T01:00:20.970Z",
  "categories": [
    {
      "name": "AI Semiconductors",
      "id": "semiconductor",
      "stocks": [
        {
          "symbol": "NVDA",
          "name": "NVIDIA",
          "price": 174.4,
          "change": 9.230000000000018,
          "changePercent": 5.588181873221541
        },
        {
          "symbol": "AMD",
          "name": "AMD",
          "price": 203.43,
          "change": 7.390000000000015,
          "changePercent": 3.769638849214454
        },
        {
          "symbol": "INTC",
          "name": "Intel",
          "price": 44.13,
          "change": 2.940000000000005,
          "changePercent": 7.137654770575394
        },
        {
          "symbol": "QCOM",
          "name": "Qualcomm",
          "price": 128.78,
          "change": 1.710000000000008,
          "changePercent": 1.3457149602581318
        },
        {
          "symbol": "AVGO",
          "name": "Broadcom",
          "price": 309.51,
          "change": 16.099999999999966,
          "changePercent": 5.487202208513672
        },
        {
          "symbol": "TSM",
          "name": "TSMC",
          "price": 337.95,
          "change": 21.44999999999999,
          "changePercent": 6.777251184834119
        },
        {
          "symbol": "ARM",
          "name": "Arm Holdings",
          "price": 151.28,
          "change": 14.319999999999993,
          "changePercent": 10.455607476635508
        }
      ]
    },
    {
      "name": "Big Tech",
      "id": "bigtech",
      "stocks": [
        {
          "symbol": "MSFT",
          "name": "Microsoft",
          "price": 370.17,
          "change": 11.210000000000036,
          "changePercent": 3.1229106307109533
        },
        {
          "symbol": "GOOGL",
          "name": "Alphabet",
          "price": 287.56,
          "change": 14.060000000000002,
          "changePercent": 5.140767824497259
        },
        {
          "symbol": "META",
          "name": "Meta",
          "price": 572.13,
          "change": 35.75,
          "changePercent": 6.6650508967523034
        },
        {
          "symbol": "AMZN",
          "name": "Amazon",
          "price": 208.27,
          "change": 7.320000000000022,
          "changePercent": 3.6426971883553234
        },
        {
          "symbol": "AAPL",
          "name": "Apple",
          "price": 253.79,
          "change": 7.159999999999997,
          "changePercent": 2.9031342496857624
        }
      ]
    },
    {
      "name": "AI Pure-Play",
      "id": "ai-pure",
      "stocks": [
        {
          "symbol": "PLTR",
          "name": "Palantir",
          "price": 146.28,
          "change": 8.72999999999999,
          "changePercent": 6.346782988004354
        },
        {
          "symbol": "AI",
          "name": "C3.ai",
          "price": 8.42,
          "change": 0.6299999999999999,
          "changePercent": 8.08729139922978
        },
        {
          "symbol": "SNOW",
          "name": "Snowflake",
          "price": 150.82,
          "change": -2.8499999999999943,
          "changePercent": -1.854623543957828
        },
        {
          "symbol": "PATH",
          "name": "UiPath",
          "price": 11.1,
          "change": 0.23000000000000043,
          "changePercent": 2.1159153633854686
        },
        {
          "symbol": "DDOG",
          "name": "Datadog",
          "price": 118.05,
          "change": 2.239999999999995,
          "changePercent": 1.9342025731802044
        }
      ]
    }
  ]
}