{
  "updatedAt": "2026-03-02T05:00:19.998Z",
  "regions": [
    {
      "region": "US",
      "label": "United States",
      "icon": "🇺🇸",
      "items": [
        {
          "title": "luke kennard",
          "traffic": "500+",
          "articles": [
            {
              "title": "Lakers News: JJ Redick Commends Luke Kennard For Creating ‘Blender’ In Offense",
              "url": "https://lakersnation.com/lakers-news-jj-redick-commends-luke-kennard-for-creating-blender-in-offense/",
              "source": "LakersNation.com"
            },
            {
              "title": "Luke Kennard just justified Lakers’ bold trade in one game",
              "url": "https://lakeshowlife.com/los-angeles-lakers-luke-kennard-just-justified-bold-trade-one-game-warriors",
              "source": "Lake Show Life"
            },
            {
              "title": "Lakers are making a painful Luke Kennard realization that Pistons fans know too well",
              "url": "https://pistonpowered.com/lakers-are-making-painful-luke-kennard-realization-pistons-fans-know-well",
              "source": "PistonPowered"
            }
          ]
        },
        {
          "title": "nicholas braimbridge tony cooper",
          "traffic": "2000+",
          "articles": [
            {
              "title": "&apos;Bridgerton&apos; Honors Nicholas Braimbridge and Tony Cooper: Season 4 Finale Tributes Explained",
              "url": "https://www.tvinsider.com/1248199/who-is-nicholas-braimbridge-tony-cooper-bridgerton-tribute-season-4-finale/",
              "source": "TV Insider"
            },
            {
              "title": "&apos;Bridgerton&apos; Nicholas Braimbridge Tribute: What Happened to Him?",
              "url": "https://www.aol.com/bridgerton-nicholas-braimbridge-tribute-happened-152355493.html",
              "source": "AOL.com"
            },
            {
              "title": "Who Are Nicholas Braimbridge and Tony Cooper From ‘Bridgerton’ Season 4 Tribute?",
              "url": "https://www.cosmopolitan.com/entertainment/celebs/a70540543/bridgerton-who-are-nicholas-braimbridge-tony-cooper/",
              "source": "Cosmopolitan"
            }
          ]
        }
      ]
    },
    {
      "region": "JP",
      "label": "Japan",
      "icon": "🇯🇵",
      "items": []
    },
    {
      "region": "KR",
      "label": "South Korea",
      "icon": "🇰🇷",
      "items": []
    }
  ]
}