{
  "updatedAt": "2026-03-19T14:00:24.229Z",
  "regions": [
    {
      "region": "US",
      "label": "United States",
      "icon": "🇺🇸",
      "items": [
        {
          "title": "lara spencer",
          "traffic": "500+",
          "articles": [
            {
              "title": "Lara Spencer Is Bringing Thrifting Back to TV—Here Are Her Best Tips for Shopping Secondhand with Confidence",
              "url": "https://www.yahoo.com/entertainment/tv/articles/lara-spencer-bringing-thrifting-back-000000227.html",
              "source": "Yahoo"
            },
            {
              "title": "The Dish: A Greenwich shop will be featured on &apos;That Thrifting Show with Lara Spencer&apos;",
              "url": "https://www.greenwichtime.com/news/article/the-dish-lara-spencer-greenwich-22075166.php",
              "source": "Greenwich Time"
            },
            {
              "title": "How to watch That Thrifting Show outside the US",
              "url": "https://blog.reelgood.com/how-to-watch-that-thrifting-show-outside-the-us",
              "source": "UpNext by Reelgood"
            }
          ]
        },
        {
          "title": "stock market news",
          "traffic": "5000+",
          "articles": [
            {
              "title": "Stocks fall again as oil prices rise, Dow loses 200 points: Live updates",
              "url": "https://www.cnbc.com/2026/03/18/stock-market-today-live-updates.html",
              "source": "CNBC"
            },
            {
              "title": "Dow, S&amp;P 500 And Nasdaq Fall To 2026 Low: Inflation Fears And Oil Rattle Markets",
              "url": "https://www.forbes.com/sites/tylerroush/2026/03/19/dow-sp-500-and-nasdaq-fall-to-2026-low-inflation-fears-and-oil-rattle-markets/",
              "source": "Forbes"
            },
            {
              "title": "Stock Market Today: Oil Soars Past $110, Dow Futures Slip — Live Updates",
              "url": "https://www.wsj.com/livecoverage/stock-market-today-dow-sp-500-nasdaq-03-19-2026?gaa_at=eafs&amp;gaa_n=AWEtsqdfVnvhQPdFcvcK2Y85pLoU4pu0v4NfOH448wq9C3eQBh_h7xjM7fKq&amp;gaa_ts=69bc0471&amp;gaa_sig=2MCvKC6Un9gU5OUoxEMjeEF3T_VyBJ7v0PzCyrD2jyhl4VyCk8XYhAYGro_eE4zIppJVu7E0UjTuikqSsuWyRw%3D%3D",
              "source": "WSJ"
            }
          ]
        },
        {
          "title": "tsa wait times airports",
          "traffic": "5000+",
          "articles": [
            {
              "title": "Could your airport close if TSA screeners don’t show up to work? Here’s what experts say",
              "url": "https://www.cnn.com/2026/03/18/us/tsa-airports-close",
              "source": "CNN"
            },
            {
              "title": "Over a third of TSA officers call out at 3 major U.S. airports in single day as ‌funding standoff continues",
              "url": "https://www.cbsnews.com/news/tsa-officers-third-call-out-major-us-airports-funding-standoff/",
              "source": "CBS News"
            },
            {
              "title": "How to monitor airport security lines at US airports while TSA officers go without pay",
              "url": "https://apnews.com/article/tsa-checking-airport-security-wait-times-28b98c06d14f9cd4e27332550e5cba94",
              "source": "AP News"
            }
          ]
        },
        {
          "title": "kate mara",
          "traffic": "2000+",
          "articles": [
            {
              "title": "Kate Mara Explains How Martha Stewart Randomly Ended Up at Her Intimate Birthday Party",
              "url": "https://www.imdb.com/news/ni65755188/?ref_=nwc_art_perm",
              "source": "IMDb"
            },
            {
              "title": "Kate Mara reveals Martha Stewart crashed her birthday party: &apos;We&apos;ll sit in the back row&apos;",
              "url": "https://ew.com/kate-mara-reveals-martha-stewart-crashed-her-birthday-party-11928075",
              "source": "Entertainment Weekly"
            },
            {
              "title": "Kate Mara’s Birthday Party Got Crashed by Martha Stewart",
              "url": "https://www.yahoo.com/entertainment/videos/kate-mara-birthday-party-got-203500026.html",
              "source": "Yahoo"
            }
          ]
        }
      ]
    },
    {
      "region": "JP",
      "label": "Japan",
      "icon": "🇯🇵",
      "items": []
    },
    {
      "region": "KR",
      "label": "South Korea",
      "icon": "🇰🇷",
      "items": []
    }
  ]
}