{
  "updatedAt": "2026-03-30T02:00:23.455Z",
  "regions": [
    {
      "region": "US",
      "label": "United States",
      "icon": "🇺🇸",
      "items": [
        {
          "title": "justin hartley",
          "traffic": "200+",
          "articles": [
            {
              "title": "CBS Announces Permanent Casting Change To Justin Hartley’s Tracker",
              "url": "https://www.imdb.com/es/news/ni65769798/",
              "source": "IMDb"
            },
            {
              "title": "‘Tracker’ Ups Chris Lee To Series Regular For Season 3",
              "url": "https://deadline.com/2026/03/tracker-chris-lee-promoted-series-regular-season-3-1236767030/",
              "source": "Deadline"
            },
            {
              "title": "TV Casting Shakeups: Tracker Changes, God of War News, and More",
              "url": "https://www.thetvcave.com/post/tv-casting-shakeups-tracker-changes-god-of-war-news-and-more",
              "source": "The TV Cave"
            }
          ]
        },
        {
          "title": "hailey bieber",
          "traffic": "500+",
          "articles": [
            {
              "title": "Hailey Bieber Cuddles Up With Justin Bieber in a Sweet New Photo",
              "url": "https://www.elle.com/culture/celebrities/a70875771/hailey-justin-bieber-photo-jack-dad-mumma/",
              "source": "ELLE"
            },
            {
              "title": "Hailey Bieber cuddles up with Justin Bieber in a sweet new photo",
              "url": "https://www.msn.com/en-us/lifestyle/lifestyle-buzz/hailey-bieber-cuddles-up-with-justin-bieber-in-a-sweet-new-photo/ar-AA1ZFjh8",
              "source": "MSN"
            },
            {
              "title": "Hailey Bieber Cuddles Up With Justin Bieber in a Sweet New Photo",
              "url": "https://www.aol.com/articles/hailey-bieber-cuddles-justin-bieber-145446873.html",
              "source": "AOL.com"
            }
          ]
        }
      ]
    },
    {
      "region": "JP",
      "label": "Japan",
      "icon": "🇯🇵",
      "items": []
    },
    {
      "region": "KR",
      "label": "South Korea",
      "icon": "🇰🇷",
      "items": []
    }
  ]
}