{
  "updatedAt": "2026-03-07T14:00:18.801Z",
  "regions": [
    {
      "region": "US",
      "label": "United States",
      "icon": "🇺🇸",
      "items": [
        {
          "title": "cagliari vs como",
          "traffic": "1000+",
          "articles": [
            {
              "title": "Cuándo juegan Cagliari vs. Como por la Serie A 2025/26: equipo, fecha, hora y TV en vivo",
              "url": "https://espndeportes.espn.com/futbol/italia/nota/_/id/16391999/cagliari-vs-como-fecha-28-serie-a-equipo-fecha-hora-y-tv-en-vivo",
              "source": "ESPN Deportes"
            },
            {
              "title": "Dónde ver al Como 1907 buscar asaltar Cerdeña para blindar su sueño de Champions",
              "url": "https://caribepeninsular.mx/donde-ver-al-como-1907-buscar-asaltar-cerdena-para-blindar-su-sueno-de-champions/",
              "source": "Caribe Peninsular"
            },
            {
              "title": "Cagliari - Como en directo",
              "url": "https://www.elmundo.es/deportes/futbol/serie-a/cagliari-como/2026/03/07/01_0107_20260307_124_1065-directo.html",
              "source": "El Mundo"
            }
          ]
        },
        {
          "title": "arkansas vs missouri prediction",
          "traffic": "200+",
          "articles": [
            {
              "title": "Mizzou&apos;s SEC Tournament fate hangs in the balance with final home game against No. 20 Arkansas",
              "url": "https://www.columbiamissourian.com/sports/mizzou_mens_basketball/mizzous-sec-tournament-fate-hangs-in-the-balance-with-final-home-game-against-no-20/article_c0f06c95-ebe1-4e65-95c2-c0628c3f892c.html",
              "source": "Columbia Missourian"
            },
            {
              "title": "MBB Preview: Arkansas at Missouri; Coach Calipari 1 Win Shy of 900",
              "url": "https://arkansasrazorbacks.com/mbb-preview-arkansas-at-missouri-coach-calipari-1-win-shy-of-900/",
              "source": "Arkansas Razorbacks"
            },
            {
              "title": "Report: Arkansas basketball&apos;s Darius Acuff out for Missouri game",
              "url": "https://www.wholehogsports.com/news/2026/mar/06/report-arkansas-basketballs-darius-acuff-doubtful-for-missouri-game/",
              "source": "Whole Hog Sports"
            }
          ]
        }
      ]
    },
    {
      "region": "JP",
      "label": "Japan",
      "icon": "🇯🇵",
      "items": []
    },
    {
      "region": "KR",
      "label": "South Korea",
      "icon": "🇰🇷",
      "items": []
    }
  ]
}