{
  "updatedAt": "2026-03-03T14:00:23.580Z",
  "regions": [
    {
      "region": "US",
      "label": "United States",
      "icon": "🇺🇸",
      "items": [
        {
          "title": "college board",
          "traffic": "1000+",
          "articles": [
            {
              "title": "Next Yavapai College Board meeting to be in person",
              "url": "https://www.dcourier.com/news/next-yavapai-college-board-meeting-to-be-in-person/article_c586dc56-e934-5598-9433-5935fce1ab44.html",
              "source": "Prescott Daily Courier"
            },
            {
              "title": "Yavapai College",
              "url": "https://www.dcourier.com/news/yavapai-college/image_a2dde936-4342-5919-91ab-e42c648665de.html",
              "source": "Prescott Daily Courier"
            },
            {
              "title": "Midland College Board approves drilling agreement for the campus",
              "url": "https://www.firstalert7.com/video/2026/03/02/midland-college-board-approves-drilling-agreement-campus/",
              "source": "CBS7"
            }
          ]
        }
      ]
    },
    {
      "region": "JP",
      "label": "Japan",
      "icon": "🇯🇵",
      "items": [
        {
          "title": "persija jakarta vs borneo fc",
          "traffic": "200+",
          "articles": []
        }
      ]
    },
    {
      "region": "KR",
      "label": "South Korea",
      "icon": "🇰🇷",
      "items": []
    }
  ]
}