{
  "updatedAt": "2026-04-26T02:00:20.902Z",
  "regions": [
    {
      "region": "US",
      "label": "United States",
      "icon": "🇺🇸",
      "items": [
        {
          "title": "anthony edwards",
          "traffic": "10000+",
          "articles": [
            {
              "title": "Anthony Edwards&apos; Baby Mamas Join Forces to Take on NBA Star in Court",
              "url": "https://www.tmz.com/2026/04/25/anthony-edwards-baby-mamas-join-forces-in-court/",
              "source": "TMZ"
            },
            {
              "title": "Anthony Edwards under pressure as Ayesha Howard and Alexandria Desroches connect in tense child support c",
              "url": "https://timesofindia.indiatimes.com/sports/nba/top-stories/anthony-edwards-under-pressure-as-ayesha-howard-and-alexandria-desroches-connect-in-tense-child-support-court-battle/articleshow/130520160.cms",
              "source": "The Times of India"
            },
            {
              "title": "Two mothers of Anthony Edwards&apos; children team up in court",
              "url": "https://www.hoopshype.com/story/sports/nba/rumors/2026/04/25/two-mothers-of-anthony-edwards-children-team-up-in-court/89793653007/",
              "source": "HoopsHype"
            }
          ]
        },
        {
          "title": "anthony edwards injury",
          "traffic": "2000+",
          "articles": [
            {
              "title": "Nuggets in greater trouble after latest Anthony Edwards update",
              "url": "https://basketnews.com/news-245887-nuggets-in-greater-trouble-after-latest-anthony-edwards-update.html",
              "source": "BasketNews.com"
            },
            {
              "title": "Timberwolves&apos; Anthony Edwards: Fades injury report",
              "url": "https://www.cbssports.com/fantasy/basketball/news/timberwolves-anthony-edwards-fades-injury-report/",
              "source": "CBS Sports"
            },
            {
              "title": "Anthony Edwards helped off the court in Game 4 on Saturday",
              "url": "https://www.twincities.com/2026/04/25/anthony-edwards-helped-off-the-court-in-game-4-on-saturday/",
              "source": "Pioneer Press"
            }
          ]
        },
        {
          "title": "charlize theron",
          "traffic": "5000+",
          "articles": [
            {
              "title": "‘Apex’ Review: Charlize Theron’s Australian Adventure on Netflix",
              "url": "https://www.wsj.com/arts-culture/film/apex-review-charlize-therons-australian-adventure-on-netflix-61a0f77f",
              "source": "WSJ"
            },
            {
              "title": "&apos;Apex&apos;s brutal ending, explained",
              "url": "https://mashable.com/article/apex-netflix-ending-explained",
              "source": "Mashable"
            },
            {
              "title": "Apex Ending Explained: How Charlize Theron Fights Her Way to Freedom",
              "url": "https://www.netflix.com/tudum/articles/apex-ending-explained",
              "source": "Netflix"
            }
          ]
        }
      ]
    },
    {
      "region": "JP",
      "label": "Japan",
      "icon": "🇯🇵",
      "items": []
    },
    {
      "region": "KR",
      "label": "South Korea",
      "icon": "🇰🇷",
      "items": []
    }
  ]
}