{
  "updatedAt": "2026-04-16T19:00:24.158Z",
  "regions": [
    {
      "region": "US",
      "label": "United States",
      "icon": "🇺🇸",
      "items": [
        {
          "title": "why are the sirens going off",
          "traffic": "1000+",
          "articles": [
            {
              "title": "Here’s why tornado sirens will blare across Minnesota, even on a warm and sunny day",
              "url": "https://www.startribune.com/heres-why-tornado-sirens-will-blare-across-minnesota-even-on-a-warm-and-sunny-day/601748902",
              "source": "Star Tribune"
            },
            {
              "title": "Wisconsin statewide tornado drills canceled",
              "url": "https://www.wmtv15news.com/2026/04/15/wisconsin-statewide-tornado-drill-canceled/",
              "source": "WMTV 15 NEWS"
            },
            {
              "title": "Severe Weather Cancels Statewide Severe Weather Exercise",
              "url": "https://whbl.com/2026/04/16/severe-weather-cancels-statewide-severe-weather-exercise/",
              "source": "WHBL News"
            }
          ]
        },
        {
          "title": "charlotte flair",
          "traffic": "500+",
          "articles": [
            {
              "title": "Charlotte Flair Breaks Character: The Real Woman Behind WWE’s ‘Queen’",
              "url": "https://www.si.com/wrestling/video/charlotte-flair-breaks-character-the-real-woman-behind-wwe-s-queen-01kp66hwj620mfw3z569",
              "source": "Sports Illustrated"
            },
            {
              "title": "Charlotte Flair Recalls Unwritten Rules Coming To WWE, ‘You Could Not Hit One Move Someone Else Does’",
              "url": "https://www.fightful.com/wrestling/charlotte-flair-recalls-unwritten-rules-coming-to-wwe-you-could-not-hit-one-move-someone-else-does/",
              "source": "Fightful"
            },
            {
              "title": "Charlotte Flair Opens Up About The &quot;Ric Flair In A Wig&quot; Comments",
              "url": "https://wrestlingnews.co/wwe-news/charlotte-flair-opens-about-ric-flair-wig-comments/",
              "source": "Wrestling News Co"
            }
          ]
        }
      ]
    },
    {
      "region": "JP",
      "label": "Japan",
      "icon": "🇯🇵",
      "items": []
    },
    {
      "region": "KR",
      "label": "South Korea",
      "icon": "🇰🇷",
      "items": []
    }
  ]
}