{
  "updatedAt": "2026-03-29T23:00:20.365Z",
  "regions": [
    {
      "region": "US",
      "label": "United States",
      "icon": "🇺🇸",
      "items": [
        {
          "title": "stars vs flyers",
          "traffic": "500+",
          "articles": [
            {
              "title": "RAV4 Things: Flyers vs. Stars",
              "url": "https://www.nhl.com/flyers/news/rav4-things-flyers-vs-stars",
              "source": "NHL.com"
            },
            {
              "title": "NHL Predictions: Expert Picks on Sunday, March 29",
              "url": "https://vsin.com/nhl/nhl-predictions-expert-picks-on-sunday-march-29/",
              "source": "VSiN"
            },
            {
              "title": "Mikko Rantanen, Stars out to subdue charging Flyers",
              "url": "https://www.cbssports.com/nhl/news/mikko-rantanen-stars-out-to-subdue-charging-flyers/",
              "source": "CBS Sports"
            }
          ]
        },
        {
          "title": "carroll county tn",
          "traffic": "200+",
          "articles": [
            {
              "title": "Dash cam video shows deadly Clarksville school bus crash in Carroll County",
              "url": "https://www.wsmv.com/2026/03/29/dash-cam-video-shows-deadly-clarksville-school-bus-crash-carroll-county/",
              "source": "WSMV"
            },
            {
              "title": "2 students dead and at least 7 other people injured in Tennessee school bus crash",
              "url": "https://www.cnn.com/2026/03/28/us/tennessee-school-bus-crash",
              "source": "CNN"
            },
            {
              "title": "‘My heart is heavy’: Mourners gather in vigil for Kenwood Middle students killed in bus crash | PHOTOS",
              "url": "https://clarksvillenow.com/local/mourners-gather-for-vigil-at-kenwood-middle-to-remember-students-killed-in-bus-crash-photos/",
              "source": "Clarksville Now"
            }
          ]
        }
      ]
    },
    {
      "region": "JP",
      "label": "Japan",
      "icon": "🇯🇵",
      "items": []
    },
    {
      "region": "KR",
      "label": "South Korea",
      "icon": "🇰🇷",
      "items": []
    }
  ]
}