{
  "updatedAt": "2026-02-25T23:00:20.014Z",
  "regions": [
    {
      "region": "US",
      "label": "United States",
      "icon": "🇺🇸",
      "items": [
        {
          "title": "bridgerton season 4 part 2",
          "traffic": "10000+",
          "articles": [
            {
              "title": "&apos;Bridgerton&apos; Season 4 returns with Part 2. Here&apos;s when it comes out.",
              "url": "https://www.usatoday.com/story/entertainment/tv/2026/02/25/bridgerton-season-4-part-2-release-date/88828271007/",
              "source": "USA Today"
            },
            {
              "title": "What Time Does ‘Bridgerton’ Season 4, Part 2 Come Out On Netflix?",
              "url": "https://www.forbes.com/sites/monicamercuri/2026/02/25/what-time-does-bridgerton-season-4-part-2-come-out-on-netflix/",
              "source": "Forbes"
            },
            {
              "title": "‘Bridgerton’ Is Bringing More Fan-Favorite Hits to Its Soundtrack for Season 4 Finale",
              "url": "https://www.miamiherald.com/entertainment/article314839575.html",
              "source": "Miami Herald"
            }
          ]
        }
      ]
    },
    {
      "region": "JP",
      "label": "Japan",
      "icon": "🇯🇵",
      "items": []
    },
    {
      "region": "KR",
      "label": "South Korea",
      "icon": "🇰🇷",
      "items": [
        {
          "title": "juventus vs galatasaray",
          "traffic": "200+",
          "articles": [
            {
              "title": "Juventus 3-2 Galatasaray (5-7 agg): Italians fight back to force extra time but fall short",
              "url": "https://www.bbc.com/sport/football/live/cjd9z9k5dd2t",
              "source": "BBC"
            },
            {
              "title": "&apos;Utter disgrace!&apos; - Fans left in disbelief as Lloyd Kelly receives &apos;criminal&apos; red card in Juventus&apos; Champions League clash with Galatasaray",
              "url": "https://www.goal.com/en/lists/utter-disgrace-fans-disbelief-lloyd-kelly-criminal-red-card-juventus-champions-league-galatasaray/blt59145f9a8cf0cf37",
              "source": "Goal.com"
            },
            {
              "title": "Chiellini tells Juventus: ‘Score a goal, then we’ll see…’",
              "url": "https://football-italia.net/chiellini-tells-juventus-score-1-goal-then-see/",
              "source": "Football Italia"
            }
          ]
        }
      ]
    }
  ]
}