{
  "updatedAt": "2026-04-25T03:00:18.387Z",
  "regions": [
    {
      "region": "US",
      "label": "United States",
      "icon": "🇺🇸",
      "items": [
        {
          "title": "marcus smart",
          "traffic": "2000+",
          "articles": [
            {
              "title": "Marcus Smart&apos;s breakout game helps Lakers go up 2-0 on Rockets",
              "url": "https://www.espn.com/nba/story/_/id/48558342/marcus-smart-helps-short-handed-lakers-win-game-2-vs-rockets",
              "source": "ESPN"
            },
            {
              "title": "LeBron James gushes about former Celtics guard after Game 2 upset vs. Rockets",
              "url": "https://www.masslive.com/celtics/2026/04/lebron-james-gushes-about-former-celtics-guard-after-game-2-upset-vs-rockets.html",
              "source": "MassLive.com"
            },
            {
              "title": "Lakers coach JJ Redick cites private conversation as team wins again",
              "url": "https://www.usatoday.com/story/sports/nba/playoffs/2026/04/22/lakers-rockets-marcus-smarter-stats-jj-redick/89728711007/",
              "source": "USA Today"
            }
          ]
        },
        {
          "title": "pete crow armstrong",
          "traffic": "1000+",
          "articles": [
            {
              "title": "Will Cubs&apos; Pete Crow-Armstrong return to MLB superstar form?",
              "url": "https://www.espn.com/mlb/story/_/id/48571496/mlb-2026-pete-crow-armstrong-chicago-cubs-pca-production",
              "source": "ESPN"
            },
            {
              "title": "How Pete Crow-Armstrong is channeling his emotions for next phase with the Cubs",
              "url": "https://www.nytimes.com/athletic/7214491/2026/04/21/pete-crow-armstrong-emotions-cubs/",
              "source": "The New York Times"
            },
            {
              "title": "Cubs fans excuse for Pete Crow-Armstrong&apos;s early 2026 slump ignores a sobering reality",
              "url": "https://cubbiescrib.com/cubs-fans-excuse-for-pete-crow-armstrong-s-early-2026-slump-ignores-a-sobering-reality-01kpgqbwy7nc",
              "source": "Cubbies Crib"
            }
          ]
        },
        {
          "title": "jameson taillon",
          "traffic": "200+",
          "articles": [
            {
              "title": "Chicago Cubs at Los Angeles Dodgers Preview - 04/24/2026",
              "url": "https://www.mlb.com/stories/game-preview/823962",
              "source": "MLB"
            },
            {
              "title": "Starting lineups for Cubs at Dodgers - April 24, 2026",
              "url": "https://www.mlb.com/dodgers/video/starting-lineups-for-cubs-at-dodgers-april-24-2026?t=t119-default-vtp",
              "source": "MLB.com"
            },
            {
              "title": "Where to watch Chicago Cubs vs. Los Angeles Dodgers: Live stream, TV channel, odds for Friday, April 24",
              "url": "https://sports.yahoo.com/mlb/article/where-to-watch-chicago-cubs-vs-los-angeles-dodgers-live-stream-tv-channel-odds-for-friday-april-24-171208621.html",
              "source": "Yahoo Sports"
            }
          ]
        },
        {
          "title": "puebla - querétaro",
          "traffic": "5000+",
          "articles": [
            {
              "title": "Puebla vs Querétaro, horario, dónde ver y como llegan al duelo del Clausura 2026",
              "url": "https://www.lavozarizona.com/story/deportes/futbol/2026/04/24/puebla-vs-quertaro-horario-donde-ver-y-como-llegan-al-clausura-2026/89752584007/",
              "source": "azcentral.com and The Arizona Republic"
            },
            {
              "title": "Liga MX: Puebla vs Querétaro EN VIVO - Jornada 17 del Clausura 2026",
              "url": "https://www.eluniversal.com.mx/deportes/liga-mx-puebla-vs-queretaro-en-vivo-jornada-17-del-clausura-2026/",
              "source": "El Universal"
            },
            {
              "title": "#DudaRazonable | “La más sólida y antigua organización para la defensa de los derechos humanos en el mundo, Amnistía Internacional, publicó esta semana su informe anual” 🎙️ Lee y escucha la #opinión deCarlos Puig https://mile.io/3QvBTMz",
              "url": "https://www.facebook.com/MilenioDiario/photos/dudarazonable-la-m%C3%A1s-s%C3%B3lida-y-antigua-organizaci%C3%B3n-para-la-defensa-de-los-derech/1450203313803802/",
              "source": "Facebook"
            }
          ]
        },
        {
          "title": "will kacmarek",
          "traffic": "1000+",
          "articles": [
            {
              "title": "NFL Draft 2026 results: Dolphins continue third round with another offensive piece",
              "url": "https://sports.yahoo.com/articles/nfl-draft-2026-results-dolphins-023515250.html",
              "source": "Yahoo Sports"
            },
            {
              "title": "Dolphins&apos; Will Kacmarek: Selected by Dolphins",
              "url": "https://www.cbssports.com/fantasy/football/news/dolphins-will-kacmarek-selected-by-dolphins/",
              "source": "CBS Sports"
            },
            {
              "title": "Who is Will Kacmarek? Highlights, scouting report for the Dolphins’ draft pick",
              "url": "https://www.cleveland.com/osu/2026/04/who-is-will-kacmarek-highlights-scouting-report-for-the-dolphins-draft-pick.html",
              "source": "Cleveland.com"
            }
          ]
        }
      ]
    },
    {
      "region": "JP",
      "label": "Japan",
      "icon": "🇯🇵",
      "items": []
    },
    {
      "region": "KR",
      "label": "South Korea",
      "icon": "🇰🇷",
      "items": []
    }
  ]
}