{
  "updatedAt": "2026-02-28T10:00:20.281Z",
  "regions": [
    {
      "region": "US",
      "label": "United States",
      "icon": "🇺🇸",
      "items": [
        {
          "title": "alaska airlines flights",
          "traffic": "100+",
          "articles": [
            {
              "title": "Pilot Shouted &apos;Birds!&apos; Seconds Before Impact That Took Out 8 Canada Geese and Filled the Cockpit with Smoke",
              "url": "https://www.yahoo.com/news/articles/pilot-shouted-birds-seconds-impact-160650031.html",
              "source": "Yahoo"
            },
            {
              "title": "Flock of geese forces Alaska Airlines cargo flight to make emergency landing, NTSB report says",
              "url": "https://www.alaskasnewssource.com/2026/02/25/flock-geese-forces-alaska-airlines-cargo-flight-make-emergency-landing-ntsb-report-says/",
              "source": "Alaska&apos;s News Source"
            },
            {
              "title": "NTSB report confirms bird strike forced emergency landing of Amazon cargo plane at CVG",
              "url": "https://www.wlwt.com/article/cvg-airport-amazon-cargo-plane-emergency-landing-bird-strike/70513053",
              "source": "WLWT"
            }
          ]
        },
        {
          "title": "university of arizona",
          "traffic": "100+",
          "articles": [
            {
              "title": "Arizona softball sweeps doubleheader with 2 run-rule victories",
              "url": "https://sports.yahoo.com/articles/arizona-softball-sweeps-doubleheader-2-054347527.html",
              "source": "Yahoo Sports"
            },
            {
              "title": "Arizona softball starts Hillenbrand Invitational with 2-hitter from Rylie Holder",
              "url": "https://www.azdesertswarm.com/softball/76380/arizona-softball-starts-hillenbrand-invitational-2-hitter-holder-trice-lowe",
              "source": "Arizona Desert Swarm"
            },
            {
              "title": "No. 14 Arizona Sweeps Doubleheader - University of Arizona Athletics",
              "url": "https://arizonawildcats.com/news/2026/2/27/softball-no-14-arizona-sweeps-doubleheader.aspx",
              "source": "University of Arizona Athletics"
            }
          ]
        },
        {
          "title": "saudi arabia",
          "traffic": "200+",
          "articles": [
            {
              "title": "A Trump Call Ignited Saudi-U.A.E. Feud",
              "url": "https://www.nytimes.com/2026/02/27/world/middleeast/saudi-arabia-united-arab-emirates-feud-trump-call.html",
              "source": "The New York Times"
            },
            {
              "title": "Trump told UAE leader Saudi Arabia wanted Emirates sanctioned: Report",
              "url": "https://www.middleeasteye.net/news/trump-told-uae-leader-saudi-arabia-wanted-emirates-sanctioned-report",
              "source": "Middle East Eye"
            },
            {
              "title": "Trash-Talking Trump Pushed Two Allies Into Vicious Fight",
              "url": "https://www.thedailybeast.com/trash-talking-trump-pushed-two-allies-into-vicious-fight/",
              "source": "The Daily Beast"
            }
          ]
        }
      ]
    },
    {
      "region": "JP",
      "label": "Japan",
      "icon": "🇯🇵",
      "items": []
    },
    {
      "region": "KR",
      "label": "South Korea",
      "icon": "🇰🇷",
      "items": []
    }
  ]
}