{
  "updatedAt": "2026-04-30T04:00:49.024Z",
  "regions": [
    {
      "region": "US",
      "label": "United States",
      "icon": "🇺🇸",
      "items": [
        {
          "title": "earthquake now",
          "traffic": "2000+",
          "articles": [
            {
              "title": "A preliminary magnitude 2.8 earthquake has struck near Granite Bay",
              "url": "https://www.abc10.com/article/weather/earthquakes/a-preliminary-magnitude-28-earthquake-has-struck-near-granite-bay/103-44acfe6e-4f45-4984-9363-878b9e1a6d35",
              "source": "ABC10"
            },
            {
              "title": "Earthquake Outside Granite Bay Shakes Roseville and Rocklin Residents",
              "url": "https://rosevilletoday.com/news/roseville/earthquake-granite-bay-shakes-roseville-and-rocklin-residents/",
              "source": "Roseville Today"
            },
            {
              "title": "Earthquake of magnitude 2.4 detected near Brentwood, CA on April 29",
              "url": "https://www.sacbee.com/news/california/earthquakes/article315581651.html",
              "source": "Sacramento Bee"
            }
          ]
        },
        {
          "title": "earthquake",
          "traffic": "2000+",
          "articles": [
            {
              "title": "3.4 magnitude earthquake jolts area southeast of Silver Springs",
              "url": "https://mynews4.com/news/local/33-magnitude-earthquake-jolts-area-southeast-of-silver-springs",
              "source": "KRNV My News 4"
            },
            {
              "title": "Magnitude 4.4 is latest in series of earthquakes to hit Nevada",
              "url": "https://www.foxweather.com/weather-news/magnitude-4-7-earthquake-shakes-las-vegas",
              "source": "FOX Weather"
            },
            {
              "title": "4.7 Magnitude Earthquake Strikes Nevada Near Alamo, USGS Reports",
              "url": "https://gvwire.com/2026/04/29/4-7-magnitude-earthquake-strikes-nevada-near-alamo-usgs-reports/",
              "source": "GV Wire"
            }
          ]
        },
        {
          "title": "earthquake near me",
          "traffic": "500+",
          "articles": [
            {
              "title": "Moderate Magnitude 4.1 Earthquake 31 km Southeast of Tartagal, Argentina",
              "url": "https://www.volcanodiscovery.com/earthquake/news/300982/Moderate-magnitude-41-earthquake-31-km-southeast-of-Tartagal-Argentina.html",
              "source": "Volcano Discovery"
            },
            {
              "title": "Seismic-like event, possible earthquake, reported about 10 minutes ago near Tartagal, Salta, Argentina",
              "url": "https://www.volcanodiscovery.com/earthquake/news/300980/Seismic-like-event-possible-earthquake-reported-about-10-minutes-ago-near-Tartagal-Salta-Argentina.html",
              "source": "Volcano Discovery"
            },
            {
              "title": "A preliminary magnitude 2.8 earthquake has struck near Granite Bay",
              "url": "https://www.abc10.com/article/weather/earthquakes/a-preliminary-magnitude-28-earthquake-has-struck-near-granite-bay/103-44acfe6e-4f45-4984-9363-878b9e1a6d35",
              "source": "ABC10"
            }
          ]
        },
        {
          "title": "charles barkley",
          "traffic": "500+",
          "articles": [
            {
              "title": "Charles Barkley gets fed up with himself over nonstop commercial appearances",
              "url": "https://www.marca.com/en/basketball/nba/2026/04/30/charles-barkley-gets-fed-up-with-himself-over-nonstop-commercial-appearances.html",
              "source": "MARCA"
            },
            {
              "title": "Charles Barkley Critiques Own NCAA Tournament Commercial Frequency",
              "url": "https://www.asatunews.co.id/en/charles-barkley-ncaa-commercial-critique",
              "source": "AsatuNews.co.id"
            },
            {
              "title": "Charles Barkley Critiques Repetitive TV Commercials During March Madness",
              "url": "https://www.harianbasis.co/en/barkley-critiques-march-madness-commercials",
              "source": "HarianBasis.co"
            }
          ]
        },
        {
          "title": "earthquakes today",
          "traffic": "200+",
          "articles": [
            {
              "title": "Map: 6.1-Magnitude Earthquake Shakes Northern Japan",
              "url": "https://www.nytimes.com/interactive/2026/04/26/world/quake-tracker-northern-japan.html",
              "source": "The New York Times"
            },
            {
              "title": "Weather agency ends 1-week advisory after M7.7 quake in northeastern Japan",
              "url": "https://english.kyodonews.net/articles/-/74933",
              "source": "Japan Wire by Kyodo News"
            },
            {
              "title": "Magnitude 6.2 quake shakes Hokkaido",
              "url": "https://www.japantimes.co.jp/news/2026/04/27/japan/japan-hokkaido-quake/",
              "source": "The Japan Times"
            }
          ]
        },
        {
          "title": "mariska hargitay",
          "traffic": "2000+",
          "articles": [
            {
              "title": "Mariska Hargitay says cut Benson and Stabler “SVU ”kiss was shot &apos;a couple different ways&apos;",
              "url": "https://www.yahoo.com/entertainment/tv/articles/mariska-hargitay-says-cut-benson-154017675.html",
              "source": "Yahoo"
            },
            {
              "title": "Mariska Hargitay Says Chris Meloni SVU Kiss Filmed, More in Interview",
              "url": "https://www.hollywoodreporter.com/movies/movie-news/mariska-hargitay-christopher-meloni-svu-kiss-interview-1236579222/",
              "source": "The Hollywood Reporter"
            },
            {
              "title": "Mariska Hargitay exposes who cut Christopher Meloni kissing scene on ‘Law &amp; Order: SVU’",
              "url": "https://pagesix.com/2026/04/29/entertainment/mariska-hargitay-says-dick-wolf-cut-law-order-svu-christopher-meloni-kiss-scene/",
              "source": "Page Six"
            }
          ]
        }
      ]
    },
    {
      "region": "JP",
      "label": "Japan",
      "icon": "🇯🇵",
      "items": []
    },
    {
      "region": "KR",
      "label": "South Korea",
      "icon": "🇰🇷",
      "items": [
        {
          "title": "삼성전자 실적",
          "traffic": "1000+",
          "articles": [
            {
              "title": "삼성, 반도체로만 53조 벌었다…&apos;40만전자&apos; 전망까지 [종합]",
              "url": "https://www.hankyung.com/article/202604307313g",
              "source": "한국경제"
            },
            {
              "title": "삼성전자, HBM4 올해 물량 완판…장기공급계약 추진 중(종합2보)",
              "url": "https://www.news1.kr/industry/general-industry/6154059",
              "source": "뉴스1"
            },
            {
              "title": "삼성전자, 1분기 반도체 영업이익 53.7조...엔비디아 바짝 따라잡았다",
              "url": "https://www.chosun.com/economy/tech_it/2026/04/30/Y6R5KMOMMFDSLMVR7EYDSWO4NY/",
              "source": "조선일보"
            }
          ]
        }
      ]
    }
  ]
}