{
  "updatedAt": "2026-03-15T08:00:18.717Z",
  "regions": [
    {
      "region": "US",
      "label": "United States",
      "icon": "🇺🇸",
      "items": [
        {
          "title": "ryan garcia",
          "traffic": "100+",
          "articles": [
            {
              "title": "Henry Garcia Claims Ryan Garcia Is Bigger Draw",
              "url": "https://www.boxingnews24.com/2026/03/ryan-garcias-father-insists-he-remains-the-a-side-over-devin-haney/",
              "source": "Boxing News 24"
            },
            {
              "title": "Video: Oscar De La Hoya talks Vergil Ortiz, Garcia vs Haney and more",
              "url": "https://www.fightmag.com/video-oscar-de-la-hoya-talks-vergil-ortiz-garcia-vs-haney-and-more/",
              "source": "Fightmag"
            },
            {
              "title": "Ryan Garcia ‘makes it clear’ who he now wants to fight next",
              "url": "https://boxingnewsonline.net/news/ryan-garcia-on-who-he-now-wants-next/",
              "source": "Boxing News Online"
            }
          ]
        }
      ]
    },
    {
      "region": "JP",
      "label": "Japan",
      "icon": "🇯🇵",
      "items": []
    },
    {
      "region": "KR",
      "label": "South Korea",
      "icon": "🇰🇷",
      "items": []
    }
  ]
}